biosaic/__init__.py
biosaic/_dna.py
biosaic/_main.py
biosaic/_protein.py
biosaic/_rna.py
biosaic/visual/cgr.py
biosaic/visual/cmap.py
biosaic-0.1.5.dist-info/licenses/LICENSE
biosaic-0.1.5.dist-info/METADATA
biosaic-0.1.5.dist-info/WHEEL
biosaic-0.1.5.dist-info/top_level.txt
biosaic-0.1.5.dist-info/RECORD
