Metadata-Version: 2.4
Name: biosaic
Version: 0.1.5
Summary: Biosaic: a lightweight DNA and protein k-mer tokenizer with pre-trained vocab support.
Author-email: Shivendra S <shivharsh44@gmail.com>
License-Expression: Apache-2.0
Project-URL: Homepage, https://github.com/delveopers/biosaic
Project-URL: Source, https://github.com/delveopers/biosaic
Project-URL: Documentation, https://devsorg.vercel.app/docs/Biosaic/Usage.md
Keywords: bioinformatics,tokenizer,dna,protein,kmer,machine-learning
Classifier: Programming Language :: Python :: 3
Classifier: Programming Language :: Python :: 3.10
Classifier: Programming Language :: Python :: 3.11
Classifier: Programming Language :: Python :: 3.12
Classifier: Programming Language :: Python :: 3.13
Classifier: Intended Audience :: Science/Research
Classifier: Development Status :: 5 - Production/Stable
Classifier: Topic :: Scientific/Engineering :: Bio-Informatics
Requires-Python: >=3.10
License-File: LICENSE
Requires-Dist: requests>=2.25.1
Dynamic: license-file
